setup.py
cary_perdiemcommand/__init__.py
cary_perdiemcommand/__main__.py
cary_perdiemcommand/perdiem_database.py
cary_perdiemcommand/perdiem_scraper.py
cary_perdiemcommand.egg-info/PKG-INFO
cary_perdiemcommand.egg-info/SOURCES.txt
cary_perdiemcommand.egg-info/dependency_links.txt
cary_perdiemcommand.egg-info/entry_points.txt
cary_perdiemcommand.egg-info/requires.txt
cary_perdiemcommand.egg-info/top_level.txt
cary_perdiemcommand/templates/html_template.html
cary_perdiemcommand/templates/plaintext_template.txt